o2o/__init__.py
o2o/analyzer.py
o2o/demo.py
o2o/estimator.py
o2o/hawkes_model.stan
o2o/simulator.py
o2o_process-3.10.30.dist-info/licenses/LICENSE
o2o_process-3.10.30.dist-info/METADATA
o2o_process-3.10.30.dist-info/WHEEL
o2o_process-3.10.30.dist-info/entry_points.txt
o2o_process-3.10.30.dist-info/top_level.txt
o2o_process-3.10.30.dist-info/RECORD
