Metadata-Version: 2.4
Name: o2o-process
Version: 3.10.30
Summary: Tools for simulating and analyzing the spillover between online and offline activities
Author: Youness Diouane
Author-email: taykileo@gmail.com
License: MIT
Classifier: Programming Language :: Python :: 3
Classifier: Operating System :: OS Independent
Requires-Python: >=3.7
License-File: LICENSE
Requires-Dist: numpy
Requires-Dist: pandas
Requires-Dist: matplotlib
Requires-Dist: cmdstanpy
Requires-Dist: nest_asyncio
Dynamic: license-file
